{"organisation_key":"15d10c80-9060-45a0-aa37-2e45eab6b723","organisation_title":"ECOBIO UMR 6553 CNRS Universit\u00e9 de Rennes 1","organisation_description":"L\u2019unit\u00e9 ECOBIO \u00abEcosyst\u00e8mes, Biodiversit\u00e9, Evolution\u00bb est une unit\u00e9 pluridisciplinaire d\u2019\u00e9cologie dont l'axe f\u00e9d\u00e9rateur a pour objet la biodiversit\u00e9 des \u00e9cosyst\u00e8mes continentaux et insulaires, de la mol\u00e9cule \u00e0 l\u2019\u00e9cosyst\u00e8me. Elle y est analys\u00e9e tant dans son organisation spatiale, depuis le nano-microm\u00e8tre jusqu\u2019au paysage, que dans son \u00e9volution temporelle et sa dynamique fonctionnelle. Ainsi, i) analyser les capacit\u00e9s d\u2019adaptation (comportementales et\/ou physiologiques) des organismes et leurs strat\u00e9gies d\u2019\u00e9volution face aux changements climatiques et\/ou aux pressions anthropiques (agriculture, urbanisation), ii) identifier les m\u00e9canismes qui r\u00e9gissent l\u2019assemblage des communaut\u00e9s et la co-existence de la biodiversit\u00e9, iii) quantifier le r\u00f4le de la biodiversit\u00e9 dans le fonctionnement des \u00e9cosyst\u00e8mes et son lien avec lesservices \u00e9cosyst\u00e9miques, et iv) comprendre ses relations avec les hommes et les territoires au travers des politiques publiques par exemple, sont autant d\u2019objectifs poursuivis qui font le c\u0153ur des recherches men\u00e9es dans l\u2019unit\u00e9.","organisation_homepage":["https:\/\/ecobio.univ-rennes1.fr\/"],"organisation_datasets":[]}